Workbook

Sheet 00_PANDUAN_PENGGUNAAN
A1: SUITE TEMPLATE EXCEL SUPER LENGKAP UMKM - COOCA INDONESIA
A2: Panduan Operasional Bisnis Terpadu: Penjualan, Stok, Keuangan, HPP, SDM, Marketing, Operasional & Pajak
A3: KETERANGAN: [Hijau Muda = Kolom Input Pengguna] | [Abu-Abu Muda = Rumus Otomatis (Jangan Diubah)] | [Merah Muda = Alert / Peringatan Penting]
B5: SELAMAT DATANG DI SUITE DIGITAL OPERASIONAL BISNIS UMKM
B7: Tujuan Template | C7: Menyediakan sistem pencatatan, kalkulasi, dan analisis data bisnis UMKM siap pakai tanpa perlu keahlian rumus spreadsheet yang rumit.
B8: Prinsip Input Data | C8: Anda HANYA perlu memasukkan data pada kolom berwarna HIJAU MUDA. Semua kolom abu-abu dihitung otomatis oleh formula Excel.
B9: Navigasi Sheet | C9: Gunakan tab sheet di bagian bawah untuk berpindah antar modul manajemen (Penjualan, Stok, Kas, HPP/BEP, SDM, Marketing, Operasional, Pajak).
B10: Grafik & Analisis | C10: Dashboard Utama menyajikan ringkasan visual performa usaha secara real-time yang langsung bersumber dari sheet transaksi Anda.
B11: Penyimpanan & Keamanan | C11: Simpan salinan (backup) berkas ini secara berkala ke Google Drive / OneDrive atau storage lokal komputer Anda.
B12: Migrasi ke Sistem Cloud | C12: Bila bisnis Anda telah berkembang dan membutuhkan multi-kasir, multi-cabang, serta integrasi QRIS/WhatsApp otomatis, data template ini dapat langsung dimigrasikan ke platform COOCA (https://cooca.id).
B15: STRUKTUR MODUL DALAM WORKBOOK INI
B16: Nama Sheet | C16: Fungsi dan Fitur Modul
B17: 01_DASHBOARD | C17: Ringkasan Eksekutif, Scorecard KPI Omzet & Biaya, Grafik Penjualan dan Alokasi Beban
B18: 02_PENJUALAN_CRM | C18: Bagian A: Log Penjualan Harian, Rekap Bulanan, Database Pelanggan CRM, Komisi Sales
B19: 03_STOK_INVENTORI | C19: Bagian B: Master SKU, Kartu Stok Otomatis, Mutasi Masuk/Keluar, Restock Alert, Stock Opname
B20: 04_KEUANGAN_KAS | C20: Bagian C: Buku Kas Harian, Arus Kas, Laba Rugi Otomatis, Rekap Piutang & Utang Jatuh Tempo
B21: 05_HARGA_HPP_BEP | C21: Bagian D: Kalkulator HPP Produksi, Markup/Margin Harga Jual, Titik Impas (BEP) Unit & Rp
B22: 06_SDM_PAYROLL | C22: Bagian E: Master Karyawan, Rekap Absensi & Lembur, Perhitungan Gaji Bersih (Take Home Pay)
B23: 07_MARKETING_OMNI | C23: Bagian F: Kalender Konten Medsos, Rekap Marketplace (Shopee/Tokped/TikTok), Analisis ROAS Iklan
B24: 08_OPERASIONAL | C24: Bagian G: Checklist Buka/Tutup Toko, SOP Pekerjaan, Jadwal Servis Aset, Log Komplain Pelanggan
B25: 09_AKUNTANSI_PAJAK | C25: Bagian H: Jurnal Umum Debit/Kredit, Neraca Saldo, Penyusutan Aset, Rekap PPh Final UMKM 0.5%

Sheet 01_DASHBOARD
A1: EXECUTIVE COCKPIT & DASHBOARD KINERJA USAHA
A2: Ringkasan Indikator Kunci (KPI), Tren Penjualan Multi-Kanal & Distribusi Beban Operasional
A3: KETERANGAN: [Hijau Muda = Kolom Input Pengguna] | [Abu-Abu Muda = Rumus Otomatis (Jangan Diubah)] | [Merah Muda = Alert / Peringatan Penting]
B5: TOTAL OMZET BULAN INI | E5: TOTAL PENGELUARAN KAS | H5: LABA BERSIH ESTIMASI | K5: NILAI ASET PERSEDIAAN
B6: =SUM('02_PENJUALAN_CRM'!J6:J25) | E6: =SUM('04_KEUANGAN_KAS'!G6:G25) | H6: ='01_DASHBOARD'!B7-'01_DASHBOARD'!E7 | K6: =SUM('03_STOK_INVENTORI'!L6:L20)
B9: RINGKASAN PENJUALAN PER KANAL
B10: Kanal Penjualan | C10: Total Omzet (Rp) | D10: Persentase
B11: Toko Offline / POS | C11: 12500000 | D11: =C11/SUM($C$11:$C$15)
B12: Shopee | C12: 18200000 | D12: =C12/SUM($C$11:$C$15)
B13: Tokopedia | C13: 9400000 | D13: =C13/SUM($C$11:$C$15)
B14: TikTok Shop | C14: 14600000 | D14: =C14/SUM($C$11:$C$15)
B15: WhatsApp & B2B Direct | C15: 6300000 | D15: =C15/SUM($C$11:$C$15)
B16: TOTAL OMZET | C16: =SUM(C11:C15) | D16: =SUM(D11:D15)
B18: ALOKASI BIAYA & BEBAN USAHA
B19: Kategori Beban | C19: Jumlah (Rp) | D19: Porsi
B20: Beban Pokok Penjualan (HPP) | C20: 28500000 | D20: =C20/SUM($C$20:$C$24)
B21: Gaji Karyawan & Upah | C21: 9200000 | D21: =C21/SUM($C$20:$C$24)
B22: Sewa Tempat & Utilitas | C22: 3500000 | D22: =C22/SUM($C$20:$C$24)
B23: Pemasaran & Iklan Medsos | C23: 4200000 | D23: =C23/SUM($C$20:$C$24)
B24: Operasional, Logistik & Lainnya | C24: 2100000 | D24: =C24/SUM($C$20:$C$24)
B25: TOTAL BIAYA | C25: =SUM(C20:C24) | D25: =SUM(D20:D24)

Sheet 02_PENJUALAN_CRM
A1: BAGIAN A: PENJUALAN, PESANAN, CRM & KOMISI SALES
A2: Catatan Transaksi Harian, Status Bayar, Database Pelanggan & Komisi Tim Penjualan
A3: KETERANGAN: [Hijau Muda = Kolom Input Pengguna] | [Abu-Abu Muda = Rumus Otomatis (Jangan Diubah)] | [Merah Muda = Alert / Peringatan Penting]
A5: No | B5: Tanggal | C5: No Invoice | D5: Nama Pelanggan | E5: WhatsApp | F5: Kanal | G5: Produk / SKU | H5: Qty | I5: Harga Satuan | J5: Total Kotor | K5: Diskon (Rp) | L5: Total Bersih (Rp) | M5: Metode Bayar | N5: Status Pembayaran | O5: Sales PIC
A6: 1 | B6: 2026-10-01 | C6: INV-2026-001 | D6: Budi Santoso | E6: 081234567890 | F6: Toko Offline | G6: Kopi Susu Gula Aren | H6: 5 | I6: 18000 | J6: =H6*I6 | K6: 0 | L6: =J6-K6 | M6: QRIS | N6: Lunas | O6: Andi
A7: 2 | B7: 2026-10-01 | C7: INV-2026-002 | D7: Siti Rahma | E7: 081398765432 | F7: Shopee | G7: Biji Kopi Robusta 250g | H7: 2 | I7: 65000 | J7: =H7*I7 | K7: 5000 | L7: =J7-K7 | M7: Transfer | N7: Lunas | O7: Rina
A8: 3 | B8: 2026-10-02 | C8: INV-2026-003 | D8: Warung Berkah Bu Ani | E8: 081512345678 | F8: WhatsApp / B2B | G8: Sirup Karamel 1 Liter | H8: 10 | I8: 85000 | J8: =H8*I8 | K8: 50000 | L8: =J8-K8 | M8: Tempo (14 Hari) | N8: Belum Lunas | O8: Andi
A9: 4 | B9: 2026-10-02 | C9: INV-2026-004 | D9: Hendro Wijaya | E9: 082155558888 | F9: Tokopedia | G9: Tumbler Stainless 500ml | H9: 1 | I9: 120000 | J9: =H9*I9 | K9: 0 | L9: =J9-K9 | M9: Transfer | N9: Lunas | O9: Rina
A10: 5 | B10: 2026-10-03 | C10: INV-2026-005 | D10: Cafe Senja Bersama | E10: 081744443333 | F10: WhatsApp / B2B | G10: Kopi Robusta 1kg | H10: 6 | I10: 190000 | J10: =H10*I10 | K10: 40000 | L10: =J10-K10 | M10: Tempo (7 Hari) | N10: Belum Lunas | O10: Andi
A11: 6 | B11: 2026-10-03 | C11: INV-2026-006 | D11: Dewi Lestari | E11: 085611223344 | F11: TikTok Shop | G11: Kopi Susu Literan | H11: 2 | I11: 75000 | J11: =H11*I11 | K11: 10000 | L11: =J11-K11 | M11: Transfer | N11: Lunas | O11: Rina
A12: 7 | B12: 2026-10-04 | C12: INV-2026-007 | D12: Ahmad Fauzi | E12: 081988776655 | F12: Toko Offline | G12: Croissant Almond | H12: 4 | I12: 25000 | J12: =H12*I12 | K12: 0 | L12: =J12-K12 | M12: Tunai | N12: Lunas | O12: Andi
A13: 8 | B13: 2026-10-04 | C13: INV-2026-008 | D13: Rudy Pratama | E13: 081299887711 | F13: Shopee | G13: Drip Bag Coffee Box | H13: 3 | I13: 45000 | J13: =H13*I13 | K13: 5000 | L13: =J13-K13 | M13: Transfer | N13: Lunas | O13: Rina
G14: TOTAL KESELURUHAN: | H14: =SUM(H6:H13) | J14: =SUM(J6:J13) | K14: =SUM(K6:K13) | L14: =SUM(L6:L13)
A17: TARGET & PERHITUNGAN KOMISI TIM SALES
A18: No | B18: Nama Sales PIC | C18: Target Omzet (Rp) | D18: Realisasi Omzet (Rp) | E18: % Capaian | F18: Tarif Komisi | G18: Total Komisi Diterima (Rp)
A19: 1 | B19: Andi | C19: 20000000 | D19: =SUMIFS(L$6:L$13, O$6:O$13, "Andi") | E19: =D19/C19 | F19: 0.03 | G19: =D19*F19
A20: 2 | B20: Rina | C20: 15000000 | D20: =SUMIFS(L$6:L$13, O$6:O$13, "Rina") | E20: =D20/C20 | F20: 0.03 | G20: =D20*F20

Sheet 03_STOK_INVENTORI
A1: BAGIAN B: MANAJEMEN STOK, SKU, IN/OUT & ALERT RESTOCK
A2: Kartu Stok Otomatis, Nilai Persediaan, Monitoring Stok Minimum & Lembar Stock Opname
A3: KETERANGAN: [Hijau Muda = Kolom Input Pengguna] | [Abu-Abu Muda = Rumus Otomatis (Jangan Diubah)] | [Merah Muda = Alert / Peringatan Penting]
A5: No | B5: Kode SKU | C5: Nama Produk Barang | D5: Kategori | E5: Satuan | F5: Harga Modal (HPP) | G5: Harga Jual | H5: Stok Awal | I5: Stok Masuk | J5: Stok Keluar | K5: Sisa Stok Akhir | L5: Nilai Aset Stok (Rp) | M5: Batas Min (Alert) | N5: Status Stok
A6: 1 | B6: SKU-KOP-001 | C6: Kopi Susu Gula Aren | D6: Minuman | E6: Cup | F6: 8000 | G6: 18000 | H6: 50 | I6: 100 | J6: 85 | K6: =H6+I6-J6 | L6: =K6*F6 | M6: 20 | N6: =IF(K6<=M6, "⚠️ PERLU RESTOCK", "✅ AMAN")
A7: 2 | B7: SKU-KOP-002 | C7: Biji Kopi Robusta 250g | D7: Bahan Baku | E7: Pack | F7: 35000 | G7: 65000 | H7: 20 | I7: 30 | J7: 42 | K7: =H7+I7-J7 | L7: =K7*F7 | M7: 15 | N7: =IF(K7<=M7, "⚠️ PERLU RESTOCK", "✅ AMAN")
A8: 3 | B8: SKU-SYR-001 | C8: Sirup Karamel 1 Liter | D8: Bahan Baku | E8: Botol | F8: 55000 | G8: 85000 | H8: 10 | I8: 15 | J8: 21 | K8: =H8+I8-J8 | L8: =K8*F8 | M8: 5 | N8: =IF(K8<=M8, "⚠️ PERLU RESTOCK", "✅ AMAN")
A9: 4 | B9: SKU-TMB-001 | C9: Tumbler Stainless 500ml | D9: Merchandise | E9: Pcs | F9: 70000 | G9: 120000 | H9: 15 | I9: 10 | J9: 22 | K9: =H9+I9-J9 | L9: =K9*F9 | M9: 5 | N9: =IF(K9<=M9, "⚠️ PERLU RESTOCK", "✅ AMAN")
A10: 5 | B10: SKU-KOP-003 | C10: Kopi Robusta 1kg | D10: Bahan Baku | E10: Pack | F10: 110000 | G10: 190000 | H10: 8 | I10: 20 | J10: 24 | K10: =H10+I10-J10 | L10: =K10*F10 | M10: 6 | N10: =IF(K10<=M10, "⚠️ PERLU RESTOCK", "✅ AMAN")
A11: 6 | B11: SKU-CRS-001 | C11: Croissant Almond | D11: Pastry | E11: Pcs | F11: 12000 | G11: 25000 | H11: 30 | I11: 40 | J11: 65 | K11: =H11+I11-J11 | L11: =K11*F11 | M11: 10 | N11: =IF(K11<=M11, "⚠️ PERLU RESTOCK", "✅ AMAN")
A12: 7 | B12: SKU-DRP-001 | C12: Drip Bag Coffee Box (5ct) | D12: Kemasan | E12: Box | F12: 24000 | G12: 45000 | H12: 25 | I12: 30 | J12: 48 | K12: =H12+I12-J12 | L12: =K12*F12 | M12: 12 | N12: =IF(K12<=M12, "⚠️ PERLU RESTOCK", "✅ AMAN")
E13: TOTAL NILAI ASET: | K13: =SUM(K6:K12) | L13: =SUM(L6:L12)

Sheet 04_KEUANGAN_KAS
A1: BAGIAN C: BUKU KAS HARIAN, ARUS KAS & LABA RUGI OTOMATIS
A2: Catatan Kas Masuk / Keluar, Saldo Akumulatif, Laba Rugi Otomatis & Monitoring Utang/Piutang
A3: KETERANGAN: [Hijau Muda = Kolom Input Pengguna] | [Abu-Abu Muda = Rumus Otomatis (Jangan Diubah)] | [Merah Muda = Alert / Peringatan Penting]
A5: No | B5: Tanggal | C5: Kategori Transaksi | D5: Uraian Keterangan | E5: Akun / Dompet | F5: Kas Masuk (Rp) | G5: Kas Keluar (Rp) | H5: Saldo Berjalan (Rp) | J5: LAPORAN LABA RUGI (INCOME STATEMENT)
A6: 1 | B6: 2026-10-01 | C6: Saldo Awal | D6: Saldo Kas Tunai Kasir & Rekening BCA | E6: BCA | F6: 15000000 | G6: 0 | H6: =F6-G6 | J6: Pendapatan Usaha (Omzet Bersih) | L6: =SUM('02_PENJUALAN_CRM'!L6:L25)
A7: 2 | B7: 2026-10-01 | C7: Penjualan | D7: Penerimaan Omzet Kasir Harian | E7: Kas Tunai | F7: 2450000 | G7: 0 | H7: =H6+F7-G7 | J7: Beban Pokok Penjualan (HPP) | L7: =F8*0.45
A8: 3 | B8: 2026-10-01 | C8: Bahan Baku | D8: Belanja Susu Fresh Milk & Sirup | E8: Kas Tunai | F8: 0 | G8: 850000 | H8: =H7+F8-G8 | J8: LABA KOTOR (GROSS PROFIT) | L8: =L6-L7
A9: 4 | B9: 2026-10-02 | C9: Penjualan | D9: Pencairan Saldo ShopeePay Merchant | E9: BCA | F9: 3800000 | G9: 0 | H9: =H8+F9-G9 | J9: Beban Gaji Karyawan | L9: =SUM(G13)
A10: 5 | B10: 2026-10-02 | C10: Utilitas | D10: Pembayaran Listrik PLN & Internet Wi-Fi Toko | E10: BCA | F10: 0 | G10: 1250000 | H10: =H9+F10-G10 | J10: Beban Sewa & Utilitas | L10: =G10
A11: 6 | B11: 2026-10-03 | C11: Pemasaran | D11: Top Up Saldo Iklan Meta Ads (Instagram/FB) | E11: BCA | F11: 0 | G11: 1500000 | H11: =H10+F11-G11 | J11: Beban Pemasaran & Iklan | L11: =G11
A12: 7 | B12: 2026-10-03 | C12: Penjualan | D12: Penerimaan Pembayaran Invoice B2B Bu Ani | E12: BCA | F12: 800000 | G12: 0 | H12: =H11+F12-G12 | J12: Beban Operasional Lainnya | L12: =G8
A13: 8 | B13: 2026-10-04 | C13: Gaji | D13: Uang Makan & Lembur Karyawan Toko | E13: Kas Tunai | F13: 0 | G13: 450000 | H13: =H12+F13-G13 | J13: TOTAL BEBAN OPERASIONAL | L13: =SUM(L9:L12)
D14: TOTAL MUTASI & SALDO AKHIR: | F14: =SUM(F6:F13) | G14: =SUM(G6:G13) | H14: =H13 | J14: LABA OPERASIONAL SEBELUM PAJAK | L14: =L8-L13
J15: Pajak PPh Final UMKM 0.5% (PP 55) | L15: =L6*0.005
J16: LABA BERSIH SETELAH PAJAK (NET INCOME) | L16: =L14-L15

Sheet 05_HARGA_HPP_BEP
A1: BAGIAN D: KALKULATOR HPP PRODUK, HARGA JUAL & ANALISIS TITIK IMPAS (BEP)
A2: Perhitungan Komponen Biaya Pokok, Markup/Margin Laba, Titik Impas (BEP) Unit/Rupiah & Diskon
A3: KETERANGAN: [Hijau Muda = Kolom Input Pengguna] | [Abu-Abu Muda = Rumus Otomatis (Jangan Diubah)] | [Merah Muda = Alert / Peringatan Penting]
B5: 1. SIMULASI PERHITUNGAN HPP PER UNIT PRODUK | F5: 3. ANALISIS TITIK IMPAS / BREAK-EVEN POINT (BEP)
B6: Komponen Biaya | C6: Keterangan | D6: Biaya per Unit (Rp) | F6: Biaya Tetap Bulanan (Sewa, Gaji Tetap, Listrik) | H6: 9500000
B7: Bahan Baku Utama (Biji Kopi & Susu) | C7: Biji kopi espresso 20g + Fresh milk 150ml | D7: 5200 | F7: Harga Jual Rata-rata per Unit | H7: =D19
B8: Bahan Penolong (Sirup & Gula) | C8: Sirup karamel 20ml + Gula aren | D8: 1300 | F8: Biaya Variabel / HPP per Unit | H8: =D12
B9: Kemasan & Packaging | C9: Cup sablon 16oz + Lid seal + Sedotan | D9: 1200 | F9: Margin Kontribusi per Unit (Harga - Variabel) | H9: =H7-H8
B10: Tenaga Kerja Langsung | C10: Alokasi barista per cup | D10: 800 | F10: Rasio Margin Kontribusi (CM Ratio) | H10: =H9/H7
B11: Overhead Pabrik/Listrik/Mesin | C11: Depresiasi mesin espresso & listrik | D11: 500 | F11: BEP DALAM UNIT (Harus Jual Berapa Cup) | H11: =ROUNDUP(H6/H9, 0)
B12: TOTAL HPP PER UNIT: | D12: =SUM(D7:D11) | F12: BEP DALAM RUPIAH (Target Omzet Minimal) | H12: =H11*H7
F13: Target Penjualan Harian (30 Hari) | H13: =ROUNDUP(H11/30, 0)
B14: 2. PENENTUAN HARGA JUAL BERDASARKAN TARGET MARGIN
B15: Total HPP per Unit | D15: =D12
B16: Target Margin Keuntungan Kotor | D16: 0.5
B17: Harga Jual Rekomendasi [HPP / (1 - Margin)] | D17: =D15/(1-D16)
B18: Markup Persentase [(Harga - HPP) / HPP] | D18: =(D17-D15)/D15
B19: Harga Jual Aktual yang Ditetapkan Toko | D19: 18000
B20: Keuntungan Kotor Aktual per Unit | D20: =D19-D15

Sheet 06_SDM_PAYROLL
A1: BAGIAN E: DATA KARYAWAN, ABSENSI, LEMBUR & REKAP GAJI BERSIH
A2: Pencatatan Kehadiran, Perhitungan Gaji Pokok, Uang Lembur, Tunjangan, Potongan & Slip Gaji
A3: KETERANGAN: [Hijau Muda = Kolom Input Pengguna] | [Abu-Abu Muda = Rumus Otomatis (Jangan Diubah)] | [Merah Muda = Alert / Peringatan Penting]
A5: No | B5: ID Karyawan | C5: Nama Lengkap | D5: Jabatan | E5: Gaji Pokok (Rp) | F5: Tunjangan (Rp) | G5: Tarif Lembur/Jam | H5: Hari Hadir | I5: Jam Lembur | J5: Uang Lembur (Rp) | K5: Bonus/Komisi | L5: Potongan (Rp) | M5: Gaji Bersih Diterima (Rp)
A6: 1 | B6: EMP-001 | C6: Andi Pratama | D6: Head Barista & Sales | E6: 3500000 | F6: 500000 | G6: 25000 | H6: 26 | I6: 12 | J6: =I6*G6 | K6: 450000 | L6: 100000 | M6: =E6+F6+J6+K6-L6
A7: 2 | B7: EMP-002 | C7: Rina Marlina | D7: Kasir & Admin Medsos | E7: 3000000 | F7: 400000 | G7: 20000 | H7: 25 | I7: 8 | J7: =I7*G7 | K7: 300000 | L7: 50000 | M7: =E7+F7+J7+K7-L7
A8: 3 | B8: EMP-003 | C8: Doni Saputra | D8: Junior Barista | E8: 2800000 | F8: 300000 | G8: 20000 | H8: 24 | I8: 15 | J8: =I8*G8 | K8: 0 | L8: 50000 | M8: =E8+F8+J8+K8-L8
A9: 4 | B9: EMP-004 | C9: Maya Indah | D9: Kitchen & Pastry Cook | E9: 3200000 | F9: 450000 | G9: 22000 | H9: 26 | I9: 10 | J9: =I9*G9 | K9: 0 | L9: 0 | M9: =E9+F9+J9+K9-L9
D10: TOTAL BEBAN GAJI USAHA: | E10: =SUM(E6:E9) | M10: =SUM(M6:M9)

Sheet 07_MARKETING_OMNI
A1: BAGIAN F: MARKETING, KALENDER KONTEN & REKAP MARKETPLACE
A2: Performa Iklan ROAS, Penjualan Multi-Kanal (Shopee/Tokped/TikTok) & Jadwal Konten Medsos
A3: KETERANGAN: [Hijau Muda = Kolom Input Pengguna] | [Abu-Abu Muda = Rumus Otomatis (Jangan Diubah)] | [Merah Muda = Alert / Peringatan Penting]
B5: 1. REKAP PERFORMA BIAYA IKLAN & ROAS (RETURN ON AD SPEND)
B6: Kanal Iklan | C6: Budget Terpakai (Rp) | D6: Jumlah Klik/Leads | E6: Omzet Penjualan (Rp) | F6: Nilai ROAS | G6: Evaluasi Performa
B7: Meta Ads (Instagram & FB) | C7: 2500000 | D7: 1450 | E7: 11200000 | F7: =E7/C7 | G7: =IF(F7>=3, "✅ SANGAT PROFITABLE", IF(F7>=1.5, "⚠️ PROFIT SEDANG", "❌ RUGI / OPTIMASI"))
B8: TikTok Ads | C8: 1500000 | D8: 980 | E8: 5400000 | F8: =E8/C8 | G8: =IF(F8>=3, "✅ SANGAT PROFITABLE", IF(F8>=1.5, "⚠️ PROFIT SEDANG", "❌ RUGI / OPTIMASI"))
B9: Shopee Iklan Toko | C9: 1200000 | D9: 850 | E9: 6800000 | F9: =E9/C9 | G9: =IF(F9>=3, "✅ SANGAT PROFITABLE", IF(F9>=1.5, "⚠️ PROFIT SEDANG", "❌ RUGI / OPTIMASI"))
B12: 2. KALENDER JADWAL KONTEN MEDIA SOSIAL
B13: Tanggal Tayang | C13: Platform | D13: Pilar Konten | E13: Topik / Hook Konten | F13: Call To Action (CTA) | G13: Status
B14: 2026-10-05 | C14: Instagram Reels | D14: Edukasi | E14: 3 Tips Memilih Biji Kopi untuk Pemula | F14: Klik link bio untuk order biji kopi segar | G14: Siap Tayang
B15: 2026-10-06 | C15: TikTok Video | D15: Entertainment | E15: Behind the scene barista bikin latte art gagal | F15: Komentar latte art favorit kamu | G15: Published
B16: 2026-10-07 | C16: Instagram Feed | D16: Promosi | E16: Promo Beli 2 Gratis 1 Setiap Hari Rabu | F16: Datang langsung ke outlet hari ini! | G16: Draft
B17: 2026-10-08 | C17: TikTok Live | D17: Penjualan | E17: Live Shopping Flash Sale Kopi Literan | F17: Checkout di keranjang kuning sekarang | G17: Terjadwal

Sheet 08_OPERASIONAL
A1: BAGIAN G: OPERASIONAL TOKO, CHECKLIST SOP & LOG KOMPLAIN
A2: Standar Checklist Buka/Tutup Toko, Pemeliharaan Aset Mesin & Penanganan Komplain Pelanggan
A3: KETERANGAN: [Hijau Muda = Kolom Input Pengguna] | [Abu-Abu Muda = Rumus Otomatis (Jangan Diubah)] | [Merah Muda = Alert / Peringatan Penting]
B5: 1. CHECKLIST HARIAN BUKA & TUTUP OUTLET / TOKO
B6: No | C6: Waktu Shift | D6: Poin Pemeriksaan Pekerjaan (SOP) | E6: Penanggung Jawab | F6: Waktu Selesai | G6: Status Pekerjaan | H6: Catatan Verifikasi
B7: 1 | C7: Pagi (Buka) | D7: Nyalakan lampu, AC, dan musik latar outlet | E7: Andi | F7: 07:30 | G7: Selesai | H7: AC suhu 23C nyaman
B8: 2 | C8: Pagi (Buka) | D8: Cek kebersihan area meja, lantai, dan toilet | E8: Doni | F8: 07:45 | G8: Selesai | H8: Area bersih dan wangi
B9: 3 | C9: Pagi (Buka) | D9: Hitung modal kas kecil di laci kasir (Rp 300.000) | E9: Rina | F9: 07:50 | G9: Selesai | H9: Uang pas lembaran kecil
B10: 4 | C10: Pagi (Buka) | D10: Cek kesiapan mesin espresso & kalibrasi gilingan kopi | E10: Andi | F10: 07:55 | G10: Selesai | H10: Ekstraksi espresso 28 detik
B11: 5 | C11: Malam (Tutup) | D11: Tutup shift kasir, cetak laporan Z & hitung uang fisik | E11: Rina | F11: 22:15 | G11: Selesai | H11: Kas fisik cocok dengan sistem
B12: 6 | C12: Malam (Tutup) | D12: Bersihkan portafilter, backflush mesin & buang sampah | E12: Doni | F12: 22:30 | G12: Selesai | H12: Area bar bersih steril
B13: 7 | C13: Malam (Tutup) | D13: Pastikan semua kran air mati, matikan AC, dan kunci pintu | E13: Andi | F13: 22:45 | G13: Selesai | H13: Gembok pintu utama aman
B16: 2. LOG MONITORING & PENANGANAN KOMPLAIN PELANGGAN
B17: Tanggal | C17: Nama Pelanggan | D17: Kontak WA | E17: Saluran | F17: Keluhan / Masalah | G17: Solusi Penanganan | H17: Status
B18: 2026-10-02 | C18: Ibu Linda | D18: 081299881122 | E18: GoFood / Ojol | F18: Cup kopi bocor karena seal miring | G18: Kirim minuman pengganti + voucher Rp 20rb | H18: Selesai
B19: 2026-10-04 | C19: Pak Kevin | D19: 081822334455 | E19: Toko Langsung | F19: Pesanan croissant agak dingin | G19: Dipanaskan ulang + permohonan maaf langsung | H19: Selesai

Sheet 09_AKUNTANSI_PAJAK
A1: BAGIAN H: JURNAL UMUM, PENYUSUTAN ASET & REKAP PAJAK PPh UMKM
A2: Standar Pembukuan Debit/Kredit, Jadwal Depresiasi Aset & Rekap Pajak Final 0.5% (PP 55/2022)
A3: KETERANGAN: [Hijau Muda = Kolom Input Pengguna] | [Abu-Abu Muda = Rumus Otomatis (Jangan Diubah)] | [Merah Muda = Alert / Peringatan Penting]
B5: 1. JURNAL UMUM STANDAR AKUNTANSI (DOUBLE ENTRY)
B6: Tanggal | C6: No Bukti | D6: Nama Akun Rekening | E6: Ref | F6: Debit (Rp) | G6: Kredit (Rp) | H6: Keterangan Transaksi
B7: 2026-10-01 | C7: BKM-01 | D7: Kas Toko | E7: 101 | F7: 2450000 | G7: 0 | H7: Penerimaan penjualan harian kasir
B8: 2026-10-01 | C8: BKM-01 | D8: Pendapatan Penjualan | E8: 401 | F8: 0 | G8: 2450000 | H8: Penerimaan penjualan harian kasir
B9: 2026-10-01 | C9: BKK-01 | D9: Beban Bahan Baku (HPP) | E9: 501 | F9: 850000 | G9: 0 | H9: Belanja susu fresh milk & sirup
B10: 2026-10-01 | C10: BKK-01 | D10: Kas Toko | E10: 101 | F10: 0 | G10: 850000 | H10: Belanja susu fresh milk & sirup
B11: 2026-10-02 | C11: BKK-02 | D11: Beban Listrik & Internet | E11: 602 | F11: 1250000 | G11: 0 | H11: Pembayaran PLN & Indihome toko
B12: 2026-10-02 | C12: BKK-02 | D12: Kas Bank BCA | E12: 102 | F12: 0 | G12: 1250000 | H12: Pembayaran PLN & Indihome toko
E13: TOTAL & STATUS BALANCE: | F13: =SUM(F7:F12) | G13: =SUM(G7:G12) | H13: =IF(F13=G13, "✅ BALANCE / SEIMBANG", "❌ TIDAK BALANCE!")
B15: 2. REKAPITULASI OMZET BULANAN & PPh FINAL UMKM 0.5% (PP 55/2022)
B16: Bulan | C16: Omzet Bruto (Rp) | D16: Akumulasi Omzet (Rp) | E16: Batas Bebas Pajak (OP) | F16: Dasar Pengenaan Pajak | G16: Tarif PPh | H16: Pajak Terutang (Rp) | I16: Status Setor & NTPN
B17: Januari | C17: 35000000 | D17: =C17 | E17: 500000000 | F17: =IF(D17>E17, MIN(C17, D17-E17), 0) | G17: 0.005 | H17: =F17*G17 | I17: Lunas Disetor
B18: Februari | C18: 42000000 | D18: =D17+C18 | E18: 500000000 | F18: =IF(D18>E18, MIN(C18, D18-E18), 0) | G18: 0.005 | H18: =F18*G18 | I18: Lunas Disetor
B19: Maret | C19: 38000000 | D19: =D18+C19 | E19: 500000000 | F19: =IF(D19>E19, MIN(C19, D19-E19), 0) | G19: 0.005 | H19: =F19*G19 | I19: Lunas Disetor
B20: April | C20: 45000000 | D20: =D19+C20 | E20: 500000000 | F20: =IF(D20>E20, MIN(C20, D20-E20), 0) | G20: 0.005 | H20: =F20*G20 | I20: Lunas Disetor
B21: Mei | C21: 48000000 | D21: =D20+C21 | E21: 500000000 | F21: =IF(D21>E21, MIN(C21, D21-E21), 0) | G21: 0.005 | H21: =F21*G21 | I21: Lunas Disetor
B22: Juni | C22: 52000000 | D22: =D21+C22 | E22: 500000000 | F22: =IF(D22>E22, MIN(C22, D22-E22), 0) | G22: 0.005 | H22: =F22*G22 | I22: Lunas Disetor
B23: Juli | C23: 55000000 | D23: =D22+C23 | E23: 500000000 | F23: =IF(D23>E23, MIN(C23, D23-E23), 0) | G23: 0.005 | H23: =F23*G23 | I23: Lunas Disetor
B24: Agustus | C24: 58000000 | D24: =D23+C24 | E24: 500000000 | F24: =IF(D24>E24, MIN(C24, D24-E24), 0) | G24: 0.005 | H24: =F24*G24 | I24: Lunas Disetor
B25: September | C25: 60000000 | D25: =D24+C25 | E25: 500000000 | F25: =IF(D25>E25, MIN(C25, D25-E25), 0) | G25: 0.005 | H25: =F25*G25 | I25: Lunas Disetor
B26: Oktober | C26: 62000000 | D26: =D25+C26 | E26: 500000000 | F26: =IF(D26>E26, MIN(C26, D26-E26), 0) | G26: 0.005 | H26: =F26*G26 | I26: Lunas Disetor
B27: November | C27: 0 | D27: =D26+C27 | E27: 500000000 | F27: =IF(D27>E27, MIN(C27, D27-E27), 0) | G27: 0.005 | H27: =F27*G27 | I27: Belum Masa
B28: Desember | C28: 0 | D28: =D27+C28 | E28: 500000000 | F28: =IF(D28>E28, MIN(C28, D28-E28), 0) | G28: 0.005 | H28: =F28*G28 | I28: Belum Masa
B29: TOTAL TAHUNAN: | C29: =SUM(C17:C28) | H29: =SUM(H17:H28)
